setup.cfg
setup.py
docs/HISTORY.txt
infrae/__init__.py
infrae.plone.relations.schema.egg-info/PKG-INFO
infrae.plone.relations.schema.egg-info/SOURCES.txt
infrae.plone.relations.schema.egg-info/dependency_links.txt
infrae.plone.relations.schema.egg-info/namespace_packages.txt
infrae.plone.relations.schema.egg-info/not-zip-safe
infrae.plone.relations.schema.egg-info/requires.txt
infrae.plone.relations.schema.egg-info/top_level.txt
infrae/plone/__init__.py
infrae/plone/relations/__init__.py
infrae/plone/relations/schema/README.EXT.txt
infrae/plone/relations/schema/README.txt
infrae/plone/relations/schema/__init__.py
infrae/plone/relations/schema/_context.py
infrae/plone/relations/schema/_fields.py
infrae/plone/relations/schema/_relation.py
infrae/plone/relations/schema/configure.zcml
infrae/plone/relations/schema/interfaces.py
infrae/plone/relations/schema/tests.py