Metadata-Version: 1.0
Name: infrae.plone.relations.schema
Version: 1.0
Summary: Zope 3 schema for plone.app.relations items.
Home-page: http://svn.infrae.com/PloneComponent/infrae.plone.relations.schema/trunk
Author: Sylvain Viollon
Author-email: sylvain@infrae.com
License: GPL
Keywords: relationships plone schema
Platform: UNKNOWN
Classifier: Framework :: Plone
Classifier: Framework :: Zope2
Classifier: Programming Language :: Python
Classifier: Topic :: Software Development :: Libraries :: Python Modules
